FForFunAndProfitEbook/README.md
FForFunAndProfitEbook/__init__.py
FForFunAndProfitEbook/__main__.py
FForFunAndProfitEbook/file.epub
FForFunAndProfitEbook/index.html
FForFunAndProfitEbook/css/__init__.py
FForFunAndProfitEbook/css/annotations.css
FForFunAndProfitEbook/css/main.css
FForFunAndProfitEbook/css/normalize.css
FForFunAndProfitEbook/css/popup.css
FForFunAndProfitEbook/font/__init__.py
FForFunAndProfitEbook/font/fontello.eot
FForFunAndProfitEbook/font/fontello.svg
FForFunAndProfitEbook/font/fontello.ttf
FForFunAndProfitEbook/font/fontello.woff
FForFunAndProfitEbook/img/__init__.py
FForFunAndProfitEbook/img/annotator-glyph-sprite.png
FForFunAndProfitEbook/img/annotator-icon-sprite.png
FForFunAndProfitEbook/img/apple-touch-icon.png
FForFunAndProfitEbook/img/cancelfullscreen.png
FForFunAndProfitEbook/img/close.png
FForFunAndProfitEbook/img/fullscreen.png
FForFunAndProfitEbook/img/loader.gif
FForFunAndProfitEbook/img/menu-icon.png
FForFunAndProfitEbook/img/save.png
FForFunAndProfitEbook/img/saved.png
FForFunAndProfitEbook/img/settings-s.png
FForFunAndProfitEbook/img/settings.png
FForFunAndProfitEbook/img/star.png
FForFunAndProfitEbook/js/__init__.py
FForFunAndProfitEbook/js/epub.js
FForFunAndProfitEbook/js/epub.min.js
FForFunAndProfitEbook/js/epub.min.map
FForFunAndProfitEbook/js/hooks.min.js
FForFunAndProfitEbook/js/hooks.min.map
FForFunAndProfitEbook/js/reader.js
FForFunAndProfitEbook/js/reader.js.map
FForFunAndProfitEbook/js/reader.min.js
FForFunAndProfitEbook/js/reader.min.map
FForFunAndProfitEbook/js/hooks/__init__.py
FForFunAndProfitEbook/js/hooks/extensions/__init__.py
FForFunAndProfitEbook/js/hooks/extensions/highlight.js
FForFunAndProfitEbook/js/libs/__init__.py
FForFunAndProfitEbook/js/libs/jquery.min.js
FForFunAndProfitEbook/js/libs/localforage.min.js
FForFunAndProfitEbook/js/libs/screenfull.js
FForFunAndProfitEbook/js/libs/screenfull.min.js
FForFunAndProfitEbook/js/libs/zip.min.js
FForFunAndProfitEbook/js/plugins/__init__.py
f_for_fun_and_profit_ebook-2024.3.3.0.dist-info/METADATA
f_for_fun_and_profit_ebook-2024.3.3.0.dist-info/WHEEL
f_for_fun_and_profit_ebook-2024.3.3.0.dist-info/entry_points.txt
f_for_fun_and_profit_ebook-2024.3.3.0.dist-info/top_level.txt
f_for_fun_and_profit_ebook-2024.3.3.0.dist-info/RECORD
